setup.py
images/__init__.py
images/admin.py
images/models.py
images/tests.py
images/urls.py
images/views.py
images/migrations/0001_initial.py
images/migrations/0002_auto_20160323_1424.py
images/migrations/__init__.py
mysociety_django_images.egg-info/PKG-INFO
mysociety_django_images.egg-info/SOURCES.txt
mysociety_django_images.egg-info/dependency_links.txt
mysociety_django_images.egg-info/requires.txt
mysociety_django_images.egg-info/top_level.txt