Metadata-Version: 1.0
Name: mysociety-django-images
Version: 0.0.6
Summary: Attach images to any Django model, with helpful admin
Home-page: UNKNOWN
Author: Edmund von der Burg
Author-email: evdb@ecclestoad.co.uk
License: AGPL
Keywords: django images
Platform: UNKNOWN
